{
  "project_info": {
    "project_number": "206735911499",
    "project_id": "notes-aafe8",
    "storage_bucket": "notes-aafe8.firebasestorage.app"
  },
  "client": [
    {
      "client_info": {
        "mobilesdk_app_id": "1:206735911499:android:9708cd19a640a132093bce",
        "android_client_info": {
          "package_name": "com.notes"
        }
      },
      "oauth_client": [],
      "api_key": [
        {
          "current_key": "AIzaSyAEJPqMuBu-DwzaApBGyk9RmCglD0BVTsU"
        }
      ],
      "services": {
        "appinvite_service": {
          "other_platform_oauth_client": []
        }
      }
    }
  ],
  "configuration_version": "1"
}